{ "CityBuildings": [
    {
      "BuildingName": "Chapel", "BuildingTemplateID": "BT003",
      "BuildingSize": 2, "BuildingLocation": "C0001", "BuildingOwnerID": "C0001"
    },
    {
      "BuildingName": "Church", "BuildingTemplateID": "BT004",
      "BuildingSize": 1, "BuildingLocation": "C0001", "BuildingOwnerID": "C0001"
    },
    {
      "BuildingName": "Inn", "BuildingTemplateID": "BT006",
      "BuildingSize": 1, "BuildingLocation": "C0001", "BuildingOwnerID": "C0001"
    },
    {
      "BuildingName": "Wandering merchant", "BuildingTemplateID": "BT021",
      "BuildingSize": 3, "BuildingLocation": "C0001", "BuildingOwnerID": "C0001"
    }
 ]
}
