{ "SettlementBuildings": [
    {
      "BuildingName": "Chapel", "BuildingTemplateID": "BT003",
      "BuildingSize": 2, "BuildingLocation": "S0001", "BuildingOwnerID": "S0001"
    },
    {
      "BuildingName": "Scribe", "BuildingTemplateID": "BT016",
      "BuildingSize": 1, "BuildingLocation": "S0001", "BuildingOwnerID": "S0001"
    },
    {
      "BuildingName": "Wandering merchant", "BuildingTemplateID": "BT021",
      "BuildingSize": 3, "BuildingLocation": "S0001", "BuildingOwnerID": "S0001"
    }
 ]
}
